pylibcue/__init__.py
pylibcue/_cue.cpython-312-darwin.so
pylibcue/_cue.pyi
pylibcue/_cue.pyx
pylibcue/_libcue.pxd
pylibcue/cueprint.py
pylibcue/mode.py
pylibcue/py.typed
pylibcue-0.5.0.dist-info/licenses/COPYING
pylibcue-0.5.0.dist-info/licenses/vendor/libcue/LICENSE
pylibcue-0.5.0.dist-info/METADATA
pylibcue-0.5.0.dist-info/WHEEL
pylibcue-0.5.0.dist-info/entry_points.txt
pylibcue-0.5.0.dist-info/top_level.txt
pylibcue-0.5.0.dist-info/RECORD
