Metadata-Version: 2.4
Name: pylibcue
Version: 0.5.0
Summary: CUE sheet parser library for Python.
Author-email: Cycloctane <Cycloctane@octane.top>
License-Expression: GPL-2.0-only
Project-URL: Homepage, https://github.com/Cycloctane/pylibcue
Project-URL: Repository, https://github.com/Cycloctane/pylibcue.git
Project-URL: Changelog, https://github.com/Cycloctane/pylibcue/blob/main/CHANGELOG.rst
Keywords: cue,libcue,cuetools,audio,music,cd,metadata
Classifier: Development Status :: 4 - Beta
Classifier: Topic :: Utilities
Classifier: Topic :: Multimedia
Classifier: Topic :: Multimedia :: Sound/Audio :: CD Audio
Classifier: Topic :: Multimedia :: Sound/Audio :: CD Audio :: CD Ripping
Classifier: Topic :: Software Development :: Libraries
Classifier: Programming Language :: Python :: 3
Classifier: Programming Language :: Python :: 3.10
Classifier: Programming Language :: Python :: 3.11
Classifier: Programming Language :: Python :: 3.12
Classifier: Programming Language :: Python :: 3.13
Classifier: Programming Language :: Python :: 3.14
Classifier: Programming Language :: Cython
Classifier: Programming Language :: C
Classifier: Operating System :: Microsoft :: Windows
Classifier: Operating System :: POSIX :: Linux
Classifier: Operating System :: MacOS
Requires-Python: >=3.10
License-File: COPYING
License-File: vendor/libcue/LICENSE
Dynamic: license-file
